<root>

<container name="right container">
	<position>
		<x_pos>0.638925485964</x_pos>
		<y_pos>-0.465340804281</y_pos>
		<z_pos>0.177431542806</z_pos>
	</position>
	<orientation>
		<x_orient>0.996145357763</x_orient>
		<y_orient>0.0730689605286</y_orient>
		<z_orient>-0.0468014234695</z_orient>
		<w_orient>-0.0128444530736</w_orient>
	</orientation>
</container><container name="left container">
	<position>
		<x_pos>0.472388884892</x_pos>
		<y_pos>0.693064259912</y_pos>
		<z_pos>0.124097228924</z_pos>
	</position>
	<orientation>
		<x_orient>0.678829377952</x_orient>
		<y_orient>0.734210064855</y_orient>
		<z_orient>0.00494579426966</z_orient>
		<w_orient>0.0100893713412</w_orient>
	</orientation>
</container></root>